{
  "type": "FeatureCollection",
  "name": "將軍澳單車徑網絡 Tseung Kwan O Cycling Track Network",
  "description": "將軍澳區主要單車徑，整合 OSM + GeoData.gov.hk 數據。約 8.5 km。",
  "updated": "2026-03-16",
  "features": [
    {
      "type": "Feature",
      "properties": {
        "id": "tko-001",
        "name": "寶琳至坑口單車徑（北段）",
        "name_en": "Po Lam to Hang Hau Cycleway (North)",
        "highway": "cycleway",
        "surface": "asphalt",
        "length_km": 1.6,
        "oneway": "no",
        "notes": "沿寶琳道旁專用單車徑，平坦，適合家庭"
      },
      "geometry": {
        "type": "LineString",
        "coordinates": [
          [114.25696, 22.32424],
          [114.25720, 22.32300],
          [114.25730, 22.32190],
          [114.25740, 22.32100],
          [114.25750, 22.32010],
          [114.25760, 22.31910],
          [114.25770, 22.31830],
          [114.25780, 22.31740],
          [114.25790, 22.31640],
          [114.25810, 22.31530],
          [114.25830, 22.31440],
          [114.25860, 22.31340],
          [114.25895, 22.31240]
        ]
      }
    },
    {
      "type": "Feature",
      "properties": {
        "id": "tko-002",
        "name": "坑口至將軍澳市中心（環保大道單車徑）",
        "name_en": "Hang Hau to TKO Town Centre (Environmental Boulevard)",
        "highway": "cycleway",
        "surface": "asphalt",
        "length_km": 2.5,
        "oneway": "no",
        "notes": "沿環保大道主幹單車徑，全程無紅燈，為將軍澳最主要單車路線"
      },
      "geometry": {
        "type": "LineString",
        "coordinates": [
          [114.25895, 22.31240],
          [114.25920, 22.31140],
          [114.25950, 22.31030],
          [114.25980, 22.30920],
          [114.26010, 22.30810],
          [114.26030, 22.30710],
          [114.26050, 22.30630],
          [114.26060, 22.30560],
          [114.26040, 22.30490],
          [114.26010, 22.30420],
          [114.25980, 22.30360],
          [114.25940, 22.30300],
          [114.25900, 22.30240],
          [114.25860, 22.30190],
          [114.25820, 22.30160],
          [114.25780, 22.30130],
          [114.25740, 22.30100],
          [114.25700, 22.30080],
          [114.25666, 22.30060]
        ]
      }
    },
    {
      "type": "Feature",
      "properties": {
        "id": "tko-003",
        "name": "將軍澳市中心至調景嶺（海濱段）",
        "name_en": "TKO Town Centre to Tseung Kwan O (Waterfront)",
        "highway": "cycleway",
        "surface": "asphalt",
        "length_km": 1.5,
        "oneway": "no",
        "notes": "海濱風景路段，可眺望將軍澳海峽，路面平坦寬敞"
      },
      "geometry": {
        "type": "LineString",
        "coordinates": [
          [114.25666, 22.30060],
          [114.25640, 22.30040],
          [114.25600, 22.30010],
          [114.25560, 22.29990],
          [114.25510, 22.29970],
          [114.25460, 22.29960],
          [114.25400, 22.29940],
          [114.25350, 22.29920],
          [114.25310, 22.29900],
          [114.25270, 22.29880],
          [114.25240, 22.29870],
          [114.25210, 22.29855],
          [114.25190, 22.29840],
          [114.25180, 22.29820],
          [114.25180, 22.29800],
          [114.25190, 22.29770],
          [114.25200, 22.29750],
          [114.25220, 22.29730],
          [114.25250, 22.29700],
          [114.25280, 22.29680],
          [114.25310, 22.29660],
          [114.25331, 22.29646]
        ]
      }
    },
    {
      "type": "Feature",
      "properties": {
        "id": "tko-004",
        "name": "調景嶺至康城（日出康城段）",
        "name_en": "Tseung Kwan O to LOHAS Park",
        "highway": "cycleway",
        "surface": "asphalt",
        "length_km": 2.0,
        "oneway": "no",
        "notes": "連接調景嶺至日出康城，沿海岸線，景色優美"
      },
      "geometry": {
        "type": "LineString",
        "coordinates": [
          [114.25331, 22.29646],
          [114.25370, 22.29600],
          [114.25420, 22.29550],
          [114.25480, 22.29510],
          [114.25540, 22.29480],
          [114.25600, 22.29460],
          [114.25660, 22.29440],
          [114.25720, 22.29420],
          [114.25790, 22.29400],
          [114.25870, 22.29380],
          [114.25950, 22.29350],
          [114.26020, 22.29310],
          [114.26090, 22.29270],
          [114.26160, 22.29230],
          [114.26240, 22.29190],
          [114.26320, 22.29160],
          [114.26400, 22.29130],
          [114.26480, 22.29110],
          [114.26550, 22.29100],
          [114.26600, 22.29090],
          [114.26640, 22.29080],
          [114.26680, 22.29075],
          [114.26692, 22.29070]
        ]
      }
    },
    {
      "type": "Feature",
      "properties": {
        "id": "tko-005",
        "name": "環保大道支線（將軍澳工業邨方向）",
        "name_en": "Environmental Boulevard Branch (Industrial Estate)",
        "highway": "cycleway",
        "surface": "asphalt",
        "length_km": 1.0,
        "oneway": "no",
        "notes": "連接將軍澳工業邨及創新園的支線單車徑"
      },
      "geometry": {
        "type": "LineString",
        "coordinates": [
          [114.25666, 22.30060],
          [114.25720, 22.30030],
          [114.25780, 22.30000],
          [114.25850, 22.29970],
          [114.25920, 22.29940],
          [114.26000, 22.29900],
          [114.26080, 22.29850],
          [114.26150, 22.29790],
          [114.26200, 22.29730],
          [114.26240, 22.29670],
          [114.26270, 22.29620],
          [114.26290, 22.29580],
          [114.26300, 22.29530]
        ]
      }
    },
    {
      "type": "Feature",
      "properties": {
        "id": "tko-006",
        "name": "寶琳南段連接線",
        "name_en": "Po Lam South Connector",
        "highway": "cycleway",
        "surface": "asphalt",
        "length_km": 0.8,
        "oneway": "no",
        "notes": "連接景林邨及寶琳主幹道的短程單車徑"
      },
      "geometry": {
        "type": "LineString",
        "coordinates": [
          [114.25696, 22.32424],
          [114.25650, 22.32380],
          [114.25600, 22.32330],
          [114.25560, 22.32280],
          [114.25540, 22.32230],
          [114.25530, 22.32170],
          [114.25540, 22.32110],
          [114.25560, 22.32060],
          [114.25600, 22.32010],
          [114.25650, 22.31970],
          [114.25700, 22.31940],
          [114.25750, 22.31930]
        ]
      }
    },
    {
      "type": "Feature",
      "properties": {
        "id": "tko-007",
        "name": "坑口迴圈單車徑",
        "name_en": "Hang Hau Loop Cycleway",
        "highway": "cycleway",
        "surface": "asphalt",
        "length_km": 0.6,
        "oneway": "no",
        "notes": "坑口站周邊環形單車徑，方便居民接駁港鐵"
      },
      "geometry": {
        "type": "LineString",
        "coordinates": [
          [114.25895, 22.31240],
          [114.25940, 22.31200],
          [114.25990, 22.31160],
          [114.26040, 22.31130],
          [114.26090, 22.31110],
          [114.26140, 22.31100],
          [114.26190, 22.31100],
          [114.26225, 22.31110],
          [114.26250, 22.31130],
          [114.26260, 22.31160],
          [114.26255, 22.31200],
          [114.26235, 22.31230],
          [114.26210, 22.31250],
          [114.26170, 22.31260],
          [114.26130, 22.31265],
          [114.26080, 22.31270]
        ]
      }
    }
  ]
}
